hugtools/__init__.py
hugtools/_logging.py
hugtools/_version.py
hugtools/jupyter/__init__.py
hugtools/nlp/__init__.py
hugtools/profiling.py
hugtools/util.py
hugtools-0.1.0a3.dist-info/LICENSE
hugtools-0.1.0a3.dist-info/WHEEL
hugtools-0.1.0a3.dist-info/METADATA
hugtools-0.1.0a3.dist-info/RECORD
