Metadata-Version: 2.1
Name: hugtools
Version: 0.1.0a3
Summary: Some common tools that I have written over time
Home-page: https://github.com/adam-huganir/hugtools
Author: Adam Huganir
Author-email: adam@huganir.com
Requires-Python: >=3.8,<4.0
Classifier: Programming Language :: Python :: 3
Classifier: Programming Language :: Python :: 3.10
Classifier: Programming Language :: Python :: 3.8
Classifier: Programming Language :: Python :: 3.9
Project-URL: Repository, https://github.com/adam-huganir/hugtools
